ctopt/__init__.py
ctopt/contrastive_augmentation.py
ctopt/datasets.py
ctopt/log_gpu_cpu_stats.py
ctopt/losses.py
ctopt/main.py
ctopt/models.py
ctopt/preprocessing.py
ctopt/train.py
ctopt/utils.py
ctopt-0.1.2.dist-info/LICENSE
ctopt-0.1.2.dist-info/METADATA
ctopt-0.1.2.dist-info/WHEEL
ctopt-0.1.2.dist-info/entry_points.txt
ctopt-0.1.2.dist-info/RECORD
